swalign/__init__.py
swalign-0.3.6.data/scripts/swalign
swalign-0.3.6.dist-info/LICENSE
swalign-0.3.6.dist-info/METADATA
swalign-0.3.6.dist-info/WHEEL
swalign-0.3.6.dist-info/top_level.txt
swalign-0.3.6.dist-info/RECORD
