Metadata-Version: 2.1
Name: swalign
Version: 0.3.6
Summary: Smith-Waterman local aligner
Home-page: http://github.com/mbreese/swalign/
Author: Marcus Breese
Author-email: marcus@breese.com
License: UNKNOWN
Platform: UNKNOWN
Requires-Python: >=3.1
